CHANGELOG.md
LICENSE.md
docs/NAMING_CONVENTIONS.md
docs/developer_notes/ARCHITECTURE.md
docs/developer_notes/FUTURE_FEATURES.md
docs/developer_notes/INTEGRATION_TEST_GUIDE.md
docs/developer_notes/SECURITY.md
docs/developer_notes/TEST_ORGANIZATION.md
docs/user_guide/FAQ.md
docs/user_guide/INSTALLATION.md
docs/user_guide/QUICK_START.md
docs/user_guide/WORKFLOWS.md
docs/user_guide/logging-guide.md
roadmap/__init__.py
roadmap/adapters/__init__.py
roadmap/adapters/cli/__init__.py
roadmap/adapters/cli/analysis/__init__.py
roadmap/adapters/cli/analysis/commands.py
roadmap/adapters/cli/analysis/presenter.py
roadmap/adapters/cli/archive_utils.py
roadmap/adapters/cli/cli_confirmations.py
roadmap/adapters/cli/cli_error_handlers.py
roadmap/adapters/cli/cli_validators.py
roadmap/adapters/cli/comment/__init__.py
roadmap/adapters/cli/comment/commands.py
roadmap/adapters/cli/config/__init__.py
roadmap/adapters/cli/config/commands.py
roadmap/adapters/cli/core.py
roadmap/adapters/cli/crud/__init__.py
roadmap/adapters/cli/crud/base_archive.py
roadmap/adapters/cli/crud/base_create.py
roadmap/adapters/cli/crud/base_delete.py
roadmap/adapters/cli/crud/base_restore.py
roadmap/adapters/cli/crud/base_update.py
roadmap/adapters/cli/crud/crud_helpers.py
roadmap/adapters/cli/crud/crud_utils.py
roadmap/adapters/cli/crud/entity_builders.py
roadmap/adapters/cli/data/__init__.py
roadmap/adapters/cli/data/commands.py
roadmap/adapters/cli/decorators.py
roadmap/adapters/cli/dtos/__init__.py
roadmap/adapters/cli/exception_handler.py
roadmap/adapters/cli/git/__init__.py
roadmap/adapters/cli/git/commands.py
roadmap/adapters/cli/git/hooks_config.py
roadmap/adapters/cli/git/status_display.py
roadmap/adapters/cli/health/__init__.py
roadmap/adapters/cli/health/enhancer.py
roadmap/adapters/cli/health/fixer.py
roadmap/adapters/cli/health/fixers/__init__.py
roadmap/adapters/cli/health/fixers/corrupted_comments_fixer.py
roadmap/adapters/cli/health/fixers/data_integrity_fixer.py
roadmap_cli-1.0.0.dist-info/LICENSE.md
roadmap_cli-1.0.0.dist-info/METADATA
roadmap_cli-1.0.0.dist-info/WHEEL
roadmap_cli-1.0.0.dist-info/entry_points.txt
roadmap_cli-1.0.0.dist-info/RECORD
