Metadata-Version: 2.1
Name: roadmap-cli
Version: 1.0.0
Summary: Enterprise-grade command line tool for project roadmap management with GitHub integration, data visualization, and advanced analytics
Home-page: https://roadmap-cli.readthedocs.io
License: MIT
Keywords: cli,roadmap,planning,project-management,github,agile,scrum,milestone,issue-tracking,analytics,visualization,productivity
Author: Roadmap CLI Team
Author-email: contact@roadmap-cli.com
Requires-Python: >=3.10,<4.0
Classifier: Development Status :: 5 - Production/Stable
Classifier: Environment :: Console
Classifier: Intended Audience :: Developers
Classifier: Intended Audience :: Information Technology
Classifier: Intended Audience :: System Administrators
Classifier: License :: OSI Approved :: MIT License
Classifier: Operating System :: OS Independent
Classifier: Programming Language :: Python :: 3
Classifier: Programming Language :: Python :: 3.10
Classifier: Programming Language :: Python :: 3.11
Classifier: Programming Language :: Python :: 3.12
Classifier: Topic :: Office/Business :: Scheduling
Classifier: Topic :: Software Development :: Bug Tracking
Classifier: Topic :: Software Development :: Libraries :: Python Modules
Classifier: Topic :: Software Development :: Version Control :: Git
Classifier: Topic :: Utilities
Requires-Dist: GitPython (>=3.1.40,<4.0.0)
Requires-Dist: aiohttp (>=3.8.0,<4.0.0)
Requires-Dist: asyncclick (>=8.1.0,<9.0.0)
Requires-Dist: click (>=8.0.0,<9.0.0)
Requires-Dist: deprecated (>=1.2.0,<2.0.0)
Requires-Dist: diskcache (>=5.6.0,<6.0.0)
Requires-Dist: dynaconf (>=3.2.0,<4.0.0)
Requires-Dist: keyring (>=23.0.0,<26.0.0)
Requires-Dist: matplotlib (>=3.6.0,<4.0.0)
Requires-Dist: openpyxl (>=3.1.0,<4.0.0)
Requires-Dist: opentelemetry-api (>=1.20.0,<2.0.0)
Requires-Dist: opentelemetry-exporter-jaeger (>=1.20.0,<2.0.0)
Requires-Dist: opentelemetry-sdk (>=1.20.0,<2.0.0)
Requires-Dist: pandas (>=2.0.0,<3.0.0)
Requires-Dist: plotly (>=5.15.0,<6.0.0)
Requires-Dist: pydantic (>=2.0.0,<3.0.0)
Requires-Dist: python-dotenv (>=1.0.0,<2.0.0)
Requires-Dist: pyyaml (>=6.0.0,<7.0.0)
Requires-Dist: requests (>=2.28.0,<3.0.0)
Requires-Dist: rich (>=13.0.0,<15.0.0)
Requires-Dist: seaborn (>=0.12.0,<1.0.0)
Requires-Dist: structlog (>=23.0.0,<24.0.0)
Requires-Dist: tabulate (>=0.9.0,<1.0.0)
Requires-Dist: toml (>=0.10.0,<1.0.0)
Project-URL: Documentation, https://roadmap-cli.readthedocs.io
Project-URL: Repository, https://github.com/roadmap-cli/roadmap
